app_sales/Taxes.py
app_sales/__init__.py
app_sales/discounts.py
app_sales/exceptions.py
app_sales/prices.py
app_sales/sales_manager.py
sales_manager_gvp-1.0.2.dist-info/licenses/LICENSE
tests/__init__.py
tests/test_sales_manager.py
sales_manager_gvp-1.0.2.dist-info/METADATA
sales_manager_gvp-1.0.2.dist-info/WHEEL
sales_manager_gvp-1.0.2.dist-info/top_level.txt
sales_manager_gvp-1.0.2.dist-info/RECORD
